mongoz/__init__.py
mongoz/exceptions.py
mongoz/py.typed
mongoz/types.py
mongoz/conf/__init__.py
mongoz/conf/functional.py
mongoz/conf/global_settings.py
mongoz/conf/module_import.py
mongoz/core/__init__.py
mongoz/core/connection/__init__.py
mongoz/core/connection/collections.py
mongoz/core/connection/database.py
mongoz/core/connection/registry.py
mongoz/core/db/__init__.py
mongoz/core/db/datastructures.py
mongoz/core/db/documents/__init__.py
mongoz/core/db/documents/_internal.py
mongoz/core/db/documents/base.py
mongoz/core/db/documents/document.py
mongoz/core/db/documents/document_proxy.py
mongoz/core/db/documents/document_row.py
mongoz/core/db/documents/managers.py
mongoz/core/db/documents/metaclasses.py
mongoz/core/db/fields/__init__.py
mongoz/core/db/fields/base.py
mongoz/core/db/fields/core.py
mongoz/core/db/querysets/__init__.py
mongoz/core/db/querysets/base.py
mongoz/core/db/querysets/expressions.py
mongoz/core/db/querysets/operators.py
mongoz/core/db/querysets/core/constants.py
mongoz/core/db/querysets/core/manager.py
mongoz/core/db/querysets/core/protocols.py
mongoz/core/db/querysets/core/queryset.py
mongoz/core/signals/__init__.py
mongoz/core/signals/handlers.py
mongoz/core/signals/signal.py
mongoz/core/utils/__init__.py
mongoz/core/utils/documents.py
mongoz/core/utils/functional.py
mongoz/core/utils/hashable.py
mongoz/core/utils/sync.py
mongoz/protocols/__init__.py
mongoz/protocols/queryset.py
mongoz/utils/__init__.py
mongoz/utils/enums.py
mongoz/utils/inspect.py
mongoz/utils/mixins.py
mongoz-0.13.1.dist-info/METADATA
mongoz-0.13.1.dist-info/WHEEL
mongoz-0.13.1.dist-info/licenses/LICENSE
mongoz-0.13.1.dist-info/RECORD
