Metadata-Version: 2.4
Name: mongoz
Version: 0.13.1
Summary: ODM with pydantic made it simple
Project-URL: Homepage, https://github.com/dymmond/mongoz
Project-URL: Documentation, https://mongoz.dymmond.com
Project-URL: Changelog, https://mongoz.dymmond.com/release-notes/
Project-URL: Funding, https://github.com/sponsors/tarsil
Project-URL: Source, https://github.com/dymmond/mongoz
Author-email: Tiago Silva <tiago.arasivla@gmail.com>
License-File: LICENSE
Keywords: mongodb,mongoz,nosql,odm
Classifier: Development Status :: 4 - Beta
Classifier: Environment :: Web Environment
Classifier: Framework :: AnyIO
Classifier: Framework :: AsyncIO
Classifier: Intended Audience :: Developers
Classifier: Intended Audience :: Information Technology
Classifier: Intended Audience :: System Administrators
Classifier: License :: OSI Approved :: BSD License
Classifier: Operating System :: OS Independent
Classifier: Programming Language :: Python
Classifier: Programming Language :: Python :: 3
Classifier: Programming Language :: Python :: 3 :: Only
Classifier: Programming Language :: Python :: 3.10
Classifier: Programming Language :: Python :: 3.11
Classifier: Programming Language :: Python :: 3.12
Classifier: Programming Language :: Python :: 3.13
Classifier: Programming Language :: Python :: 3.14
Classifier: Topic :: Internet
Classifier: Topic :: Internet :: WWW/HTTP
Classifier: Topic :: Internet :: WWW/HTTP :: HTTP Servers
Classifier: Topic :: Software Development
Classifier: Topic :: Software Development :: Libraries
Classifier: Topic :: Software Development :: Libraries :: Application Frameworks
Classifier: Topic :: Software Development :: Libraries :: Python Modules
Classifier: Typing :: Typed
Requires-Python: >=3.10
Requires-Dist: motor>=3.3.1
Requires-Dist: orjson>=3.9.5
Requires-Dist: pydantic-settings>=2.9.0
Provides-Extra: docs
Requires-Dist: griffe-typingdoc<1.0,>=0.2.2; extra == 'docs'
Requires-Dist: mdx-include<2.0.0,>=1.4.2; extra == 'docs'
Requires-Dist: mkautodoc<0.3.0,>=0.2.0; extra == 'docs'
Requires-Dist: mkdocs-macros-plugin>=0.4.0; extra == 'docs'
Requires-Dist: mkdocs-material<10.0.0,>=9.4.4; extra == 'docs'
Requires-Dist: mkdocs-meta-descriptions-plugin>=2.3.0; extra == 'docs'
Requires-Dist: mkdocs<2.0.0,>=1.1.2; extra == 'docs'
Requires-Dist: mkdocstrings[python]<0.30.0,>=0.23.0; extra == 'docs'
Requires-Dist: pyyaml<7.0.0,>=6.0; extra == 'docs'
Provides-Extra: testing
Requires-Dist: a2wsgi<2.0.0,>1.10.0; extra == 'testing'
Requires-Dist: autoflake<3.0.0,>=2.0.2; extra == 'testing'
Requires-Dist: black<25.0,==24.1.1; extra == 'testing'
Requires-Dist: esmerald[standard]>=3.8.11; extra == 'testing'
Requires-Dist: httpx<0.30.0,>=0.25.0; extra == 'testing'
Requires-Dist: ipdb; extra == 'testing'
Requires-Dist: isort<6.0.0,>=5.12.0; extra == 'testing'
Requires-Dist: mypy==1.16.1; extra == 'testing'
Requires-Dist: pytest-asyncio<1.0.0,>=0.21.1; extra == 'testing'
Requires-Dist: pytest-cov<5.0.0,>=4.0.0; extra == 'testing'
Requires-Dist: pytest<9.0.0,>=7.2.2; extra == 'testing'
Requires-Dist: requests>=2.28.2; extra == 'testing'
Requires-Dist: ruff<1.0.0,>=0.0.256; extra == 'testing'
